awesomediff/__init__.py
awesomediff/core.py
awesomediff/func.py
awesomediff/solvers.py
tests/__init__.py
tests/test_core.py
tests/test_evaluate.py
tests/test_func.py
tests/test_function_methods.py
tests/test_functions.py
tests/test_solvers.py
tests/test_variable_methods.py
awesomediff-1.3.0.dist-info/LICENSE.txt
awesomediff-1.3.0.dist-info/METADATA
awesomediff-1.3.0.dist-info/WHEEL
awesomediff-1.3.0.dist-info/top_level.txt
awesomediff-1.3.0.dist-info/RECORD
