Metadata-Version: 2.1
Name: awesomediff
Version: 1.3.0
Summary: A package for automatic differentiation
Home-page: https://github.com/awesomediff/cs207-FinalProject
Author: Gabriel Pestre, Claire Yang, Erin Yang, Wanxi Yang
Author-email: claireyang@g.harvard.edu
License: UNKNOWN
Platform: UNKNOWN
Classifier: Programming Language :: Python :: 3
Classifier: License :: OSI Approved :: MIT License
Classifier: Operating System :: OS Independent
Requires-Python: >=3.6
Requires-Dist: numpy
